Metadata-Version: 2.1
Name: majorly-funny
Version: 0.4
Summary: A majorly funny joke
Home-page: http://github.com/storborg/funniest
Author: Flying Circus
Author-email: flyingcircus@example.com
License: MIT
Platform: UNKNOWN
